projects/alu_tcl_synthesis/src/top.sv
// 4-bit ALU with FSM Control
// This design implements a finite state machine that takes in two 4-bit inputs and an opcode,
// performs the operation, and outputs the result when done.

module alu_fsm (
    input clk,
    input rst_n,
    input start,
    input  [3:0] A,
    input  [3:0] B,
    input  [2:0] opcode, // 000: ADD, 001: SUB, 010: AND, 011: OR, 100: XOR
    output reg [3:0] result,
    output reg done
);

    parameter IDLE = 2'b00, EXECUTE = 2'b01, DONE = 2'b10;
    reg [1:0] state, next_state;

    reg [3:0] alu_result;

    // FSM state transition
    always @(posedge clk or negedge rst_n) begin
        if (!rst_n)
            state <= IDLE;
        else
            state <= next_state;
    end

    // FSM next state logic
    always@(*) begin
        next_state = state;
        case (state)
            IDLE:    if (start) next_state = EXECUTE;
            EXECUTE: next_state = DONE;
            DONE:    next_state = IDLE;
        endcase
    end

    // Datapath: ALU operations
    always@(*) begin
        alu_result = 4'b0000;
        case (opcode)
            3'b000: alu_result = A + B;       // ADD
            3'b001: alu_result = A - B;       // SUB
            3'b010: alu_result = A & B;       // AND
            3'b011: alu_result = A | B;       // OR
            3'b100: alu_result = A ^ B;       // XOR
            default: alu_result = 4'b0000;
        endcase
    end

    // Output logic
    always@(posedge clk or negedge rst_n) begin
        if (!rst_n) begin
            result <= 4'b0000;
            done <= 1'b0;
        end else begin
            case (state)
                IDLE: begin
                    result <= 4'b0000;
                    done <= 1'b0;
                end
                EXECUTE: begin
                    result <= alu_result;
                    done <= 1'b0;
                end
                DONE: begin
                    done <= 1'b1;
                end
            endcase
        end
    end

endmodule

projects/alu_tcl_synthesis/src/tb_alu_fsm.sv
`timescale 1ns / 1ps

module alu_tb;

  // Inputs
  reg clk;
  reg rst;
  reg start;
  reg [2:0] opcode;
  reg [3:0] a, b;

  // Outputs
  wire done;
  wire [3:0] result;

  // DUT instantiation
  alu_fsm dut (
    .clk(clk),
    .rst_n(rst),
    .start(start),
    .opcode(opcode),
    .A(a),
    .B(b),
    .done(done),
    .result(result)
  );

  // Clock generation
  always #5 clk = ~clk;

  // Stimulus
  initial begin
    clk = 0;
    rst = 1;     // Active low reset
    start = 0;
    opcode = 0;
    a = 0;
    b = 0;

    // Apply reset
    #10 rst = 0;  // De-assert reset
    #10 rst = 1;  // Now system starts

    // Test case 1
    apply_inputs(3'd0, 4'd10, 4'd5);    // opcode 0, A=10, B=5

    // Test case 2
    apply_inputs(3'd1, 4'd9, 4'd4);     // opcode 1, A=9, B=4

    // Test case 3
    apply_inputs(3'd2, 4'd12, 4'd6);    // opcode 2, A=12, B=6

    #20;
    $finish;
  end

  // Task to apply inputs
  task apply_inputs(input [2:0] op, input [3:0] in1, input [3:0] in2);
    begin
      @(negedge clk);
      opcode = op;
      a = in1;
      b = in2;
      start = 1;

      @(negedge clk);
      start = 0;

      // Wait until done is asserted
      wait (done == 1);
      @(posedge clk);
      $display("Opcode: %0d, A: %0d, B: %0d => Result: %0d, Done: %0d", opcode, a, b, result, done);
    end
  endtask

  // VCD dump
  initial begin
    $dumpfile("output/wave.vcd");
    $dumpvars(0, alu_tb);
  end

endmodule

projects/alu_tcl_synthesis/output/wave.vcd
$date
	Sun Jul 20 00:27:21 2025
$end
$version
	Icarus Verilog
$end
$timescale
	1ps
$end
$scope module alu_tb $end
$var wire 4 ! result [3:0] $end
$var wire 1 " done $end
$var reg 4 # a [3:0] $end
$var reg 4 $ b [3:0] $end
$var reg 1 % clk $end
$var reg 3 & opcode [2:0] $end
$var reg 1 ' rst $end
$var reg 1 ( start $end
$scope module dut $end
$var wire 4 ) A [3:0] $end
$var wire 4 * B [3:0] $end
$var wire 1 % clk $end
$var wire 3 + opcode [2:0] $end
$var wire 1 ' rst_n $end
$var wire 1 ( start $end
$var parameter 2 , DONE $end
$var parameter 2 - EXECUTE $end
$var parameter 2 . IDLE $end
$var reg 4 / alu_result [3:0] $end
$var reg 1 " done $end
$var reg 2 0 next_state [1:0] $end
$var reg 4 1 result [3:0] $end
$var reg 2 2 state [1:0] $end
$upscope $end
$scope task apply_inputs $end
$var reg 4 3 in1 [3:0] $end
$var reg 4 4 in2 [3:0] $end
$var reg 3 5 op [2:0] $end
$upscope $end
$upscope $end
$enddefinitions $end
$comment Show the parameter values. $end
$dumpall
b0 .
b1 -
b10 ,
$end
#0
$dumpvars
bx 5
bx 4
bx 3
bx 2
bx 1
bx 0
b0 /
b0 +
b0 *
b0 )
0(
1'
b0 &
0%
b0 $
b0 #
x"
bx !
$end
#5000
1%
#10000
b0 0
0"
b0 !
b0 1
b0 2
0%
0'
#15000
1%
#20000
b1 0
b1111 /
1(
b101 $
b101 *
b1010 #
b1010 )
0%
b101 4
b1010 3
b0 5
1'
#25000
b10 0
b1 2
1%
#30000
b10 0
0(
0%
#35000
b0 0
b10 2
b1111 !
b1111 1
1%
#40000
0%
#45000
1"
b0 2
1%
#50000
0%
#55000
0"
b0 !
b0 1
b100 4
b1001 3
b1 5
1%
#60000
b1 0
b101 /
1(
b100 $
b100 *
b1001 #
b1001 )
b1 &
b1 +
0%
#65000
b10 0
b1 2
1%
#70000
b10 0
0(
0%
#75000
b0 0
b10 2
b101 !
b101 1
1%
#80000
0%
#85000
1"
b0 2
1%
#90000
0%
#95000
0"
b0 !
b0 1
b110 4
b1100 3
b10 5
1%
#100000
b1 0
b100 /
1(
b110 $
b110 *
b1100 #
b1100 )
b10 &
b10 +
0%
#105000
b10 0
b1 2
1%
#110000
b10 0
0(
0%
#115000
b0 0
b10 2
b100 !
b100 1
1%
#120000
0%
#125000
1"
b0 2
1%
#130000
0%
#135000
0"
b0 !
b0 1
1%
